translation_server.py
mcp_translation_text-1.0.7.dist-info/licenses/LICENSE
mcp_translation_text-1.0.7.dist-info/METADATA
mcp_translation_text-1.0.7.dist-info/WHEEL
mcp_translation_text-1.0.7.dist-info/entry_points.txt
mcp_translation_text-1.0.7.dist-info/top_level.txt
mcp_translation_text-1.0.7.dist-info/RECORD
