Metadata-Version: 2.4
Name: mcp-translation-text
Version: 1.0.7
Summary: MCP provider wrapping the Niutrans translation API
Author-email: Niutrans <tianfengning@niutrans.com>
License: MIT
Project-URL: Homepage, https://niutrans.com
Project-URL: Source, https://github.com/niutrans/mcp-translation-text
Keywords: mcp,translation,niutrans,ai
Classifier: Programming Language :: Python :: 3
Classifier: Programming Language :: Python :: 3.10
Classifier: Programming Language :: Python :: 3.11
Classifier: Programming Language :: Python :: 3.12
Classifier: License :: OSI Approved :: MIT License
Classifier: Operating System :: OS Independent
Requires-Python: >=3.10
License-File: LICENSE
Requires-Dist: mcp[cli]>=0.2.0
Requires-Dist: requests>=2.31.0
Provides-Extra: dev
Requires-Dist: uv; extra == "dev"
Dynamic: license-file
